streamlit_indexed_db/__init__.py
streamlit_indexed_db/frontend/index.html
streamlit_indexed_db/frontend/main.js
streamlit_indexed_db/frontend/streamlit-component-lib.js
streamlit_indexed_db/frontend/style.css
streamlit_indexed_db-0.1.2.dist-info/licenses/LICENSE
streamlit_indexed_db-0.1.2.dist-info/METADATA
streamlit_indexed_db-0.1.2.dist-info/WHEEL
streamlit_indexed_db-0.1.2.dist-info/top_level.txt
streamlit_indexed_db-0.1.2.dist-info/RECORD
